<?xml version="1.0" encoding="UTF-8" ?>
<!DOCTYPE mapper PUBLIC "-//mybatis.org//DTD Mapper 3.0//EN" "http://mybatis.org/dtd/mybatis-3-mapper.dtd" >
<mapper namespace="com.xpj.mapper.UserMapper">
    <resultMap id="BaseResultMap" type="com.xpj.model.User">
        <!--
          WARNING - @mbggenerated
          This element is automatically generated by MyBatis Generator, do not modify.
        -->
        <constructor>
            <arg column="id" jdbcType="INTEGER" javaType="java.lang.Integer"/>
            <arg column="sokeNo" jdbcType="INTEGER" javaType="java.lang.Integer"/>
            <arg column="intro" jdbcType="VARCHAR" javaType="java.lang.String"/>
            <arg column="hobby" jdbcType="VARCHAR" javaType="java.lang.String"/>
            <arg column="label" jdbcType="VARCHAR" javaType="java.lang.String"/>
            <arg column="crt_time" jdbcType="TIMESTAMP" javaType="java.time.LocalDateTime"/>
            <arg column="upt_time" jdbcType="TIMESTAMP" javaType="java.time.LocalDateTime"/>
        </constructor>
    </resultMap>
    <sql id="Example_Where_Clause">
        <!--
          WARNING - @mbggenerated
          This element is automatically generated by MyBatis Generator, do not modify.
        -->
        <where>
            <foreach collection="oredCriteria" item="criteria" separator="or">
                <if test="criteria.valid">
                    <trim prefix="(" suffix=")" prefixOverrides="and">
                        <foreach collection="criteria.criteria" item="criterion">
                            <choose>
                                <when test="criterion.noValue">
                                    and ${criterion.condition}
                                </when>
                                <when test="criterion.singleValue">
                                    and ${criterion.condition} #{criterion.value}
                                </when>
                                <when test="criterion.betweenValue">
                                    and ${criterion.condition} #{criterion.value} and #{criterion.secondValue}
                                </when>
                                <when test="criterion.listValue">
                                    and ${criterion.condition}
                                    <foreach collection="criterion.value" item="listItem" open="(" close=")"
                                             separator=",">
                                        #{listItem}
                                    </foreach>
                                </when>
                            </choose>
                        </foreach>
                    </trim>
                </if>
            </foreach>
        </where>
    </sql>
    <sql id="Update_By_Example_Where_Clause">
        <!--
          WARNING - @mbggenerated
          This element is automatically generated by MyBatis Generator, do not modify.
        -->
        <where>
            <foreach collection="example.oredCriteria" item="criteria" separator="or">
                <if test="criteria.valid">
                    <trim prefix="(" suffix=")" prefixOverrides="and">
                        <foreach collection="criteria.criteria" item="criterion">
                            <choose>
                                <when test="criterion.noValue">
                                    and ${criterion.condition}
                                </when>
                                <when test="criterion.singleValue">
                                    and ${criterion.condition} #{criterion.value}
                                </when>
                                <when test="criterion.betweenValue">
                                    and ${criterion.condition} #{criterion.value} and #{criterion.secondValue}
                                </when>
                                <when test="criterion.listValue">
                                    and ${criterion.condition}
                                    <foreach collection="criterion.value" item="listItem" open="(" close=")"
                                             separator=",">
                                        #{listItem}
                                    </foreach>
                                </when>
                            </choose>
                        </foreach>
                    </trim>
                </if>
            </foreach>
        </where>
    </sql>
    <sql id="Base_Column_List">
        <!--
          WARNING - @mbggenerated
          This element is automatically generated by MyBatis Generator, do not modify.
        -->
        id, sokeNo, intro, hobby, label, crt_time, upt_time
    </sql>
    <select id="selectByExample" resultMap="BaseResultMap" parameterType="com.xpj.model.UserExample">
        <!--
          WARNING - @mbggenerated
          This element is automatically generated by MyBatis Generator, do not modify.
        -->
        select
        <if test="distinct">
            distinct
        </if>
        <include refid="Base_Column_List"/>
        from usert
        <if test="_parameter != null">
            <include refid="Example_Where_Clause"/>
        </if>
        <if test="orderByClause != null">
            order by ${orderByClause}
        </if>
    </select>
    <delete id="deleteByExample" parameterType="com.xpj.model.UserExample">
        <!--
          WARNING - @mbggenerated
          This element is automatically generated by MyBatis Generator, do not modify.
        -->
        delete from usert
        <if test="_parameter != null">
            <include refid="Example_Where_Clause"/>
        </if>
    </delete>
    <insert id="insert" parameterType="com.xpj.model.User">
        <!--
          WARNING - @mbggenerated
          This element is automatically generated by MyBatis Generator, do not modify.
        -->
        <selectKey resultType="java.lang.Integer" keyProperty="id" order="AFTER">
            SELECT LAST_INSERT_ID()
        </selectKey>
        insert into usert (sokeNo, intro, hobby,
        label, crt_time, upt_time
        )
        values (#{sokeno,jdbcType=INTEGER}, #{intro,jdbcType=VARCHAR}, #{hobby,jdbcType=VARCHAR},
        #{label,jdbcType=VARCHAR}, #{createTime,jdbcType=TIMESTAMP}, #{updateTime,jdbcType=TIMESTAMP}
        )
    </insert>
    <insert id="insertSelective" parameterType="com.xpj.model.User">
        <!--
          WARNING - @mbggenerated
          This element is automatically generated by MyBatis Generator, do not modify.
        -->
        <selectKey resultType="java.lang.Integer" keyProperty="id" order="AFTER">
            SELECT LAST_INSERT_ID()
        </selectKey>
        insert into usert
        <trim prefix="(" suffix=")" suffixOverrides=",">
            <if test="sokeno != null">
                sokeNo,
            </if>
            <if test="intro != null">
                intro,
            </if>
            <if test="hobby != null">
                hobby,
            </if>
            <if test="label != null">
                label,
            </if>
            <if test="createTime != null">
                crt_time,
            </if>
            <if test="updateTime != null">
                upt_time,
            </if>
        </trim>
        <trim prefix="values (" suffix=")" suffixOverrides=",">
            <if test="sokeno != null">
                #{sokeno,jdbcType=INTEGER},
            </if>
            <if test="intro != null">
                #{intro,jdbcType=VARCHAR},
            </if>
            <if test="hobby != null">
                #{hobby,jdbcType=VARCHAR},
            </if>
            <if test="label != null">
                #{label,jdbcType=VARCHAR},
            </if>
            <if test="createTime != null">
                #{createTime,jdbcType=TIMESTAMP},
            </if>
            <if test="updateTime != null">
                #{updateTime,jdbcType=TIMESTAMP},
            </if>
        </trim>
    </insert>
    <select id="countByExample" parameterType="com.xpj.model.UserExample" resultType="java.lang.Integer">
        <!--
          WARNING - @mbggenerated
          This element is automatically generated by MyBatis Generator, do not modify.
        -->
        select count(*) from usert
        <if test="_parameter != null">
            <include refid="Example_Where_Clause"/>
        </if>
    </select>
    <update id="updateByExampleSelective" parameterType="map">
        <!--
          WARNING - @mbggenerated
          This element is automatically generated by MyBatis Generator, do not modify.
        -->
        update usert
        <set>
            <if test="record.id != null">
                id = #{record.id,jdbcType=INTEGER},
            </if>
            <if test="record.sokeno != null">
                sokeNo = #{record.sokeno,jdbcType=INTEGER},
            </if>
            <if test="record.intro != null">
                intro = #{record.intro,jdbcType=VARCHAR},
            </if>
            <if test="record.hobby != null">
                hobby = #{record.hobby,jdbcType=VARCHAR},
            </if>
            <if test="record.label != null">
                label = #{record.label,jdbcType=VARCHAR},
            </if>
            <if test="record.createTime != null">
                crt_time = #{record.createTime,jdbcType=TIMESTAMP},
            </if>
            <if test="record.updateTime != null">
                upt_time = #{record.updateTime,jdbcType=TIMESTAMP},
            </if>
        </set>
        <if test="_parameter != null">
            <include refid="Update_By_Example_Where_Clause"/>
        </if>
    </update>
    <update id="updateByExample" parameterType="map">
        <!--
          WARNING - @mbggenerated
          This element is automatically generated by MyBatis Generator, do not modify.
        -->
        update usert
        set id = #{record.id,jdbcType=INTEGER},
        sokeNo = #{record.sokeno,jdbcType=INTEGER},
        intro = #{record.intro,jdbcType=VARCHAR},
        hobby = #{record.hobby,jdbcType=VARCHAR},
        label = #{record.label,jdbcType=VARCHAR},
        crt_time = #{record.createTime,jdbcType=TIMESTAMP},
        upt_time = #{record.updateTime,jdbcType=TIMESTAMP}
        <if test="_parameter != null">
            <include refid="Update_By_Example_Where_Clause"/>
        </if>
    </update>
</mapper>